{
    "1": ["tell me about", "details about", "planet details", "planet info", "display planet", "show planet"],
    "2": ["mass", "weight", "heavy", "weigh"],
    "3": ["check planet", "in the list", "exists", "exist", "list of planets", "in list", "a planet"],
    "4": ["moons", "how many", "how many moons", "planet's moons", "number of moons", "show number"],
    "5": ["show all", "all information", "all info", "everything", "complete system", "solar system"],
    "6": ["help", "what do I do", "how does this work", "support", "assist", "advice", "guidance", "use"],
    "7": ["clear", "refresh", "wipe"],
    "8": ["exit", "quit", "leave", "close", "bye"]
}